{
  "pageid": 1898,
  "ns": 0,
  "title": "Harold",
  "extract": "",
  "categories": [
    {
      "ns": 14,
      "title": "Category:Carbon characters"
    },
    {
      "ns": 14,
      "title": "Category:Characters who appear in multiple Fallout games"
    },
    {
      "ns": 14,
      "title": "Category:Citation needed"
    },
    {
      "ns": 14,
      "title": "Category:Fallout: Brotherhood of Steel 2 characters"
    },
    {
      "ns": 14,
      "title": "Category:Fallout: Brotherhood of Steel characters"
    },
    {
      "ns": 14,
      "title": "Category:Fallout: New California companions"
    },
    {
      "ns": 14,
      "title": "Category:Fallout 2 characters"
    },
    {
      "ns": 14,
      "title": "Category:Fallout 2 talking heads"
    },
    {
      "ns": 14,
      "title": "Category:Fallout 3 characters"
    },
    {
      "ns": 14,
      "title": "Category:Fallout Bible characters"
    }
  ],
  "contentmodel": "wikitext",
  "pagelanguage": "en",
  "pagelanguagehtmlcode": "en",
  "pagelanguagedir": "ltr",
  "touched": "2025-12-19T16:34:02Z",
  "lastrevid": 4581992,
  "length": 75258,
  "fullurl": "https://fallout.fandom.com/wiki/Harold",
  "editurl": "https://fallout.fandom.com/wiki/Harold?action=edit",
  "canonicalurl": "https://fallout.fandom.com/wiki/Harold"
}