{
  "pageid": 133723,
  "ns": 14,
  "title": "Category:Fallout weapons by skill",
  "extract": "",
  "categories": [
    {
      "ns": 14,
      "title": "Category:Fallout weapons"
    },
    {
      "ns": 14,
      "title": "Category:Weapons by game and skill"
    }
  ],
  "contentmodel": "wikitext",
  "pagelanguage": "en",
  "pagelanguagehtmlcode": "en",
  "pagelanguagedir": "ltr",
  "touched": "2025-01-19T19:20:31Z",
  "lastrevid": 4406124,
  "length": 228,
  "fullurl": "https://fallout.fandom.com/wiki/Category:Fallout_weapons_by_skill",
  "editurl": "https://fallout.fandom.com/wiki/Category:Fallout_weapons_by_skill?action=edit",
  "canonicalurl": "https://fallout.fandom.com/wiki/Category:Fallout_weapons_by_skill"
}