{
  "pageid": 1374,
  "ns": 0,
  "title": "Razlo",
  "extract": "",
  "categories": [
    {
      "ns": 14,
      "title": "Category:Articles with verified bugs"
    },
    {
      "ns": 14,
      "title": "Category:Fallout Bible human characters"
    },
    {
      "ns": 14,
      "title": "Category:Fallout characters"
    },
    {
      "ns": 14,
      "title": "Category:Fallout doctors"
    },
    {
      "ns": 14,
      "title": "Category:Fallout human characters"
    },
    {
      "ns": 14,
      "title": "Category:Shady Sands characters"
    }
  ],
  "contentmodel": "wikitext",
  "pagelanguage": "en",
  "pagelanguagehtmlcode": "en",
  "pagelanguagedir": "ltr",
  "touched": "2026-02-01T15:49:50Z",
  "lastrevid": 4531750,
  "length": 4941,
  "fullurl": "https://fallout.fandom.com/wiki/Razlo",
  "editurl": "https://fallout.fandom.com/wiki/Razlo?action=edit",
  "canonicalurl": "https://fallout.fandom.com/wiki/Razlo"
}