{
  "pageid": 2547,
  "ns": 0,
  "title": "Dispose of merchant",
  "extract": "",
  "categories": [
    {
      "ns": 14,
      "title": "Category:Fallout quests"
    },
    {
      "ns": 14,
      "title": "Category:Hub quests"
    }
  ],
  "contentmodel": "wikitext",
  "pagelanguage": "en",
  "pagelanguagehtmlcode": "en",
  "pagelanguagedir": "ltr",
  "touched": "2025-12-30T03:41:34Z",
  "lastrevid": 4530299,
  "length": 7236,
  "fullurl": "https://fallout.fandom.com/wiki/Dispose_of_merchant",
  "editurl": "https://fallout.fandom.com/wiki/Dispose_of_merchant?action=edit",
  "canonicalurl": "https://fallout.fandom.com/wiki/Dispose_of_merchant"
}